fairness_checker/__init__.py
fairness_checker/__main__.py
fairness_checker/main.py
fairness_checker/py.typed
fairness_checker-0.1.13.dist-info/LICENSE
fairness_checker-0.1.13.dist-info/METADATA
fairness_checker-0.1.13.dist-info/WHEEL
fairness_checker-0.1.13.dist-info/entry_points.txt
fairness_checker-0.1.13.dist-info/top_level.txt
fairness_checker-0.1.13.dist-info/RECORD
