Metadata-Version: 2.1
Name: fairness_checker
Version: 0.1.13
Summary: Fairnes checker
Home-page: https://github.com/RexYuan/Shu
Author: RexYuan
Author-email: hello@rexyuan.com
License: Unlicense
Requires-Python: >=3.8
License-File: LICENSE
